nurimungmung/__init__.py
nurimungmung/classExample.py
nurimungmung/temperature.py
nurimungmung-0.0.2.dist-info/METADATA
nurimungmung-0.0.2.dist-info/WHEEL
nurimungmung-0.0.2.dist-info/top_level.txt
nurimungmung-0.0.2.dist-info/RECORD
