Metadata-Version: 2.1
Name: nurimungmung
Version: 0.0.2
Summary: A conversion package
Home-page: UNKNOWN
Author: Yong-Jun Shin
Author-email: yshin1209@gmail.com
License: MIT
Keywords: conversion
Platform: UNKNOWN
Classifier: Development Status :: 3 - Alpha
Classifier: Intended Audience :: Developers
Classifier: License :: OSI Approved :: MIT License
Classifier: Programming Language :: Python :: 3
